LPBkg/__init__.py
LPBkg/detc.py
LPBkg-0.1.3.dist-info/LICENSE.txt
LPBkg-0.1.3.dist-info/METADATA
LPBkg-0.1.3.dist-info/WHEEL
LPBkg-0.1.3.dist-info/top_level.txt
LPBkg-0.1.3.dist-info/RECORD
