Metadata-Version: 2.1
Name: LPBkg
Version: 0.1.3
Summary: Detecting new signals under background mismodelling.
Home-page: https://github.com/Yorkee2018/LPBkg/tree/master/python
Author: Xiangyu Zhang, Sara Algeri
Author-email: zhan6004@umn.edu, salgeri@umn.edu
License: GNU GPLv3
Platform: UNKNOWN
Classifier: Topic :: Education
Classifier: Topic :: Scientific/Engineering :: Information Analysis
Classifier: Topic :: Scientific/Engineering :: Mathematics
Classifier: Topic :: Scientific/Engineering
Classifier: License :: OSI Approved :: GNU General Public License v3 (GPLv3)
Classifier: Programming Language :: Python
Classifier: Programming Language :: Python :: 3.6
Classifier: Programming Language :: Python :: 3.7
Classifier: Programming Language :: Python :: 3.8
Classifier: Intended Audience :: Education
Classifier: Intended Audience :: Developers
Classifier: Intended Audience :: Information Technology
Classifier: Intended Audience :: Science/Research
Requires-Dist: numpy
Requires-Dist: sympy
Requires-Dist: scipy
Requires-Dist: matplotlib
Requires-Dist: seaborn
